tbmodels/__init__.py
tbmodels/_check_compatibility.py
tbmodels/_cli.py
tbmodels/_legacy_decode.py
tbmodels/_sparse_matrix.py
tbmodels/_tb_model.py
tbmodels/exceptions.py
tbmodels/helpers.py
tbmodels/io.py
tbmodels/kdotp.py
tbmodels/py.typed
tbmodels-1.4.3.dist-info/LICENSE.txt
tbmodels-1.4.3.dist-info/METADATA
tbmodels-1.4.3.dist-info/WHEEL
tbmodels-1.4.3.dist-info/entry_points.txt
tbmodels-1.4.3.dist-info/top_level.txt
tbmodels-1.4.3.dist-info/RECORD
